kpcommons/DateProvider.py
kpcommons/Footnote.py
kpcommons/NowDateProvider.py
kpcommons/Overlap.py
kpcommons/Util.py
kpcommons/XML.py
kpcommons/XMLParseException.py
kpcommons/__init__.py
kpcommons/chunker/BaseChunker.py
kpcommons/chunker/Chunk.py
kpcommons/chunker/SentenceChunker.py
kpcommons/chunker/__init__.py
kpcommons-0.1.3.dist-info/licenses/LICENSE
kpcommons-0.1.3.dist-info/METADATA
kpcommons-0.1.3.dist-info/WHEEL
kpcommons-0.1.3.dist-info/top_level.txt
kpcommons-0.1.3.dist-info/RECORD
