Metadata-Version: 2.4
Name: KPCommons
Version: 0.1.3
Summary: A collection of reusable methods.
Author-email: Frederik Arnold <frederik.arnold@hu-berlin.de>
License:                                  Apache License
Project-URL: Homepage, https://scm.cms.hu-berlin.de/schluesselstellen/commons
Classifier: Programming Language :: Python :: 3
Classifier: License :: OSI Approved :: Apache Software License
Classifier: Operating System :: OS Independent
Requires-Python: >=3.11
License-File: LICENSE
Provides-Extra: chunk
Requires-Dist: pysbd>=0.3.4; extra == "chunk"
Dynamic: license-file
